{
  "productos": [
    {
      "id": "5b8b54a6-ce7d-40fd-9377-e4f8beff92c4",
      "name": "xbox 360",
      "precio": 2890,
      "descripcion": "consola de medio uso, pero en buen estado."
    },
    {
      "id": "b249c918-edb7-4e94-88df-c998a79998fd",
      "name": "Pc-gamer",
      "precio": 15280
    },
    {
      "id": "19e063ee-125e-4b24-a283-5c0c87456c97",
      "name": "Laptop",
      "precio": 15390,
      "descripcion": "Laptop Gamer DELL Inspiron Ryzen 5 16GB 1TB 256GB SSD Vega 8 Dell 3515-V3."
    },
    {
      "id": "910a236e-37a1-4fee-9fda-43e6ac68956c",
      "name": "Television",
      "precio": 6830,
      "descripcion": "Televisor Hisense 40 Pulgadas Hisense TV Hisense 40 Pulgadas Full HD Smart TV LED 40H5G."
    },
    {
      "id": "db4f9dc3-24b9-466b-9c28-b5673ed96559",
      "name": "Control Inalámbrico PlayStation 5 DualSense",
      "precio": 1390,
      "descripcion": "1 Control Inalámbrico y Manual de usuario"
    }
  ]
}